iant_studio/__init__.py
iant_studio/generator.py
iant_studio-0.1.0.dist-info/METADATA
iant_studio-0.1.0.dist-info/WHEEL
iant_studio-0.1.0.dist-info/top_level.txt
iant_studio-0.1.0.dist-info/RECORD
