Metadata-Version: 2.4
Name: iant-studio
Version: 0.1.0
Summary: Генератор названий для стартапов от iant
Author: iant team
Classifier: Programming Language :: Python :: 3
Classifier: License :: OSI Approved :: MIT License
Dynamic: author
Dynamic: classifier
Dynamic: summary
